[
    {
    "name": "PiP Float",
    "description": "Floating browser & multitask",
    "icon": "https://cheryl1511.github.io/pip.png",
    "store_url": "https://apps.apple.com/vn/app/pip-float-split-screen-multi/id6757326641"
  },
  {
    "name": "Split Screen",
    "description": "Multitasking & web browser",
    "icon": "https://cheryl1511.github.io/split.png",
    "store_url": "https://apps.apple.com/vn/app/multiwindow-dual-browser/id6757452082"
  },
    {
    "name": "Dual Cam front & back",
    "description": "Record videos with both 2 cameras",
    "icon": "https://cheryl1511.github.io/dual_cam.png",
    "store_url": "https://apps.apple.com/vn/app/dual-cam-front-back/id6757098667"
  },
    {
    "name": "Dual Space - Multi Accounts",
    "description": "App Cloner",
    "icon": "https://cheryl1511.github.io/dual_space.png",
    "store_url": "https://apps.apple.com/vn/app/dual-space-multi-accounts/id6756809042"
  },
  {
    "name": "Search By Image",
    "description": "Reverse image search",
    "icon": "https://cheryl1511.github.io/search_by_img.png",
    "store_url": "https://apps.apple.com/vn/app/reverse-image-search-ris/id6756606607"
  },
  {
    "name": "Image Downloader",
    "description": "Search and download images",
    "icon": "https://cheryl1511.github.io/img_downloader.png",
    "store_url": "https://apps.apple.com/vn/app/image-search-image-saver/id6756299277"
  },
  {
    "name": "Birthday Exporter",
    "description": "Facebook Birthday Exporter, Reminder",
    "icon": "https://cheryl1511.github.io/birthday.png",
    "store_url": "https://apps.apple.com/vn/app/birthday-exporter/id6744843307"
  },
  {
    "name": "Delete Messages on Messenger",
    "description": "Delete and Download Messenger Messages",
    "icon": "https://cheryl1511.github.io/del_msg.png",
    "store_url": "https://apps.apple.com/vn/app/delete-messages-on-messenger/id6743963451"
  },
  {
    "name": "Remove Inactive Friends",
    "description": "Unfriend non interactive Facebook friends",
    "icon": "https://cheryl1511.github.io/fr_ranking.png",
    "store_url": "https://apps.apple.com/vn/app/friend-ranking-removal/id6744241935"
  },
  {
    "name": "Facebook Toolkit",
    "description": "An app provides you with a powerful set of tools to help you experience and manage Facebook in the best way.",
    "icon": "https://cheryl1511.github.io/social_clean.png",
    "store_url": "https://apps.apple.com/app/clean-my-feed/id6745401921"
  },
  {
    "name": "Who Deleted Me",
    "description": "Find Who Unfriended Me on Facebook",
    "icon": "https://cheryl1511.github.io/unfriend_finder.png",
    "store_url": "https://apps.apple.com/vn/app/who-delete-me/id6743155210"
  },
  {
    "name": "Video Saver",
    "description": "Download Facebook Video",
    "icon": "https://cheryl1511.github.io/video_saver.png",
    "store_url": "https://apps.apple.com/vn/app/fvideo-saver/id6744525684"
  },
  {
    "name": "Save My Pic",
    "description": "One-click Facebook photo/video downloader for pages, profiles",
    "icon": "https://cheryl1511.github.io/savepic.png",
    "store_url": "https://apps.apple.com/vn/app/savemypic/id6753611918"
  },
  {
    "name": "Auto Group Poster",
    "description": "Automate posts to all your Facebook groups",
    "icon": "https://cheryl1511.github.io/poster.png",
    "store_url": "https://apps.apple.com/vn/app/auto-group-poster/id6753643170"
  }
  
]
